biobb_adapters/__init__.py
biobb_adapters/py.typed
biobb_adapters/cwl/biobb_amber/amber_to_pdb.cwl
biobb_adapters/cwl/biobb_amber/cestats_run.cwl
biobb_adapters/cwl/biobb_amber/cphstats_run.cwl
biobb_adapters/cwl/biobb_amber/cpptraj_randomize_ions.cwl
biobb_adapters/cwl/biobb_amber/leap_add_ions.cwl
biobb_adapters/cwl/biobb_amber/leap_build_linear_structure.cwl
biobb_adapters/cwl/biobb_amber/leap_gen_top.cwl
biobb_adapters/cwl/biobb_amber/leap_solvate.cwl
biobb_adapters/cwl/biobb_amber/nab_build_dna_structure.cwl
biobb_adapters/cwl/biobb_amber/parmed_cpinutil.cwl
biobb_adapters/cwl/biobb_amber/parmed_hmassrepartition.cwl
biobb_adapters/cwl/biobb_amber/pdb4amber_run.cwl
biobb_adapters/cwl/biobb_amber/pmemd_mdrun.cwl
biobb_adapters/cwl/biobb_amber/process_mdout.cwl
biobb_adapters/cwl/biobb_amber/process_minout.cwl
biobb_adapters/cwl/biobb_amber/sander_mdrun.cwl
biobb_adapters/cwl/biobb_analysis/cpptraj_average.cwl
biobb_adapters/cwl/biobb_analysis/cpptraj_bfactor.cwl
biobb_adapters/cwl/biobb_analysis/cpptraj_convert.cwl
biobb_adapters/cwl/biobb_analysis/cpptraj_dry.cwl
biobb_adapters/cwl/biobb_analysis/cpptraj_image.cwl
biobb_adapters/cwl/biobb_analysis/cpptraj_mask.cwl
biobb_adapters/cwl/biobb_analysis/cpptraj_rgyr.cwl
biobb_adapters/cwl/biobb_analysis/cpptraj_rms.cwl
biobb_adapters/cwl/biobb_analysis/cpptraj_rmsf.cwl
biobb_adapters/cwl/biobb_analysis/cpptraj_slice.cwl
biobb_adapters/cwl/biobb_analysis/cpptraj_snapshot.cwl
biobb_adapters/cwl/biobb_analysis/cpptraj_strip.cwl
biobb_adapters/cwl/biobb_analysis/gmx_cluster.cwl
biobb_adapters/cwl/biobb_analysis/gmx_energy.cwl
biobb_adapters/cwl/biobb_analysis/gmx_image.cwl
biobb_adapters/cwl/biobb_analysis/gmx_rgyr.cwl
biobb_adapters/cwl/biobb_analysis/gmx_rms.cwl
biobb_adapters/cwl/biobb_analysis/gmx_trjconv_str.cwl
biobb_adapters/cwl/biobb_analysis/gmx_trjconv_str_ens.cwl
biobb_adapters/cwl/biobb_analysis/gmx_trjconv_trj.cwl
biobb_adapters/cwl/biobb_chemistry/acpype_convert_amber_to_gmx.cwl
biobb_adapters-5.1.2.dist-info/licenses/LICENSE
biobb_adapters-5.1.2.dist-info/METADATA
biobb_adapters-5.1.2.dist-info/WHEEL
biobb_adapters-5.1.2.dist-info/top_level.txt
biobb_adapters-5.1.2.dist-info/RECORD
