Metadata-Version: 2.4
Name: biobb_adapters
Version: 5.1.2
Summary: Biobb_adapters is the Biobb module collection to use the building blocks with several workflow managers.
Home-page: https://github.com/bioexcel/biobb_adapters
Author: Biobb developers
Author-email: pau.andrio@bsc.es
Project-URL: Documentation, http://biobb_adapters.readthedocs.io/en/latest/
Project-URL: Bioexcel, https://bioexcel.eu/
Keywords: Bioinformatics Workflows BioExcel Compatibility
Classifier: Development Status :: 5 - Production/Stable
Classifier: Programming Language :: Python :: 3.9
Classifier: Programming Language :: Python :: 3.10
Classifier: Programming Language :: Python :: 3.11
Classifier: Programming Language :: Python :: 3.12
Classifier: License :: OSI Approved :: Apache Software License
Classifier: Operating System :: MacOS :: MacOS X
Classifier: Operating System :: POSIX
Classifier: Operating System :: Unix
Requires-Python: >=3.9,<=3.12
License-File: LICENSE
Requires-Dist: cwltool
Dynamic: author
Dynamic: author-email
Dynamic: classifier
Dynamic: description
Dynamic: description-content-type
Dynamic: home-page
Dynamic: keywords
Dynamic: license-file
Dynamic: project-url
Dynamic: requires-dist
Dynamic: requires-python
Dynamic: summary
